google/cloud/gkehub/__init__.py
google/cloud/gkehub/gapic_version.py
google/cloud/gkehub/py.typed
google/cloud/gkehub_v1/__init__.py
google/cloud/gkehub_v1/gapic_metadata.json
google/cloud/gkehub_v1/gapic_version.py
google/cloud/gkehub_v1/py.typed
google/cloud/gkehub_v1/configmanagement_v1/__init__.py
google/cloud/gkehub_v1/configmanagement_v1/gapic_metadata.json
google/cloud/gkehub_v1/configmanagement_v1/gapic_version.py
google/cloud/gkehub_v1/configmanagement_v1/py.typed
google/cloud/gkehub_v1/configmanagement_v1/services/__init__.py
google/cloud/gkehub_v1/configmanagement_v1/types/__init__.py
google/cloud/gkehub_v1/configmanagement_v1/types/configmanagement.py
google/cloud/gkehub_v1/multiclusteringress_v1/__init__.py
google/cloud/gkehub_v1/multiclusteringress_v1/gapic_metadata.json
google/cloud/gkehub_v1/multiclusteringress_v1/gapic_version.py
google/cloud/gkehub_v1/multiclusteringress_v1/py.typed
google/cloud/gkehub_v1/multiclusteringress_v1/services/__init__.py
google/cloud/gkehub_v1/multiclusteringress_v1/types/__init__.py
google/cloud/gkehub_v1/multiclusteringress_v1/types/multiclusteringress.py
google/cloud/gkehub_v1/services/__init__.py
google/cloud/gkehub_v1/services/gke_hub/__init__.py
google/cloud/gkehub_v1/services/gke_hub/async_client.py
google/cloud/gkehub_v1/services/gke_hub/client.py
google/cloud/gkehub_v1/services/gke_hub/pagers.py
google/cloud/gkehub_v1/services/gke_hub/transports/__init__.py
google/cloud/gkehub_v1/services/gke_hub/transports/base.py
google/cloud/gkehub_v1/services/gke_hub/transports/grpc.py
google/cloud/gkehub_v1/services/gke_hub/transports/grpc_asyncio.py
google/cloud/gkehub_v1/services/gke_hub/transports/rest.py
google/cloud/gkehub_v1/services/gke_hub/transports/rest_base.py
google/cloud/gkehub_v1/types/__init__.py
google/cloud/gkehub_v1/types/feature.py
google/cloud/gkehub_v1/types/membership.py
google/cloud/gkehub_v1/types/service.py
google/cloud/gkehub_v1beta1/__init__.py
google/cloud/gkehub_v1beta1/gapic_metadata.json
google_cloud_gke_hub-1.19.0.dist-info/licenses/LICENSE
google_cloud_gke_hub-1.19.0.dist-info/METADATA
google_cloud_gke_hub-1.19.0.dist-info/WHEEL
google_cloud_gke_hub-1.19.0.dist-info/top_level.txt
google_cloud_gke_hub-1.19.0.dist-info/RECORD
